{
  "attributes" : {
    "type" : "SBQQ__LookupQuery__c",
    "url" : "/services/data/v55.0/sobjects/SBQQ__LookupQuery__c/a4N5A0000009kbsUAA"
  },
  "Id" : "a4N5A0000009kbsUAA",
  "OwnerId" : "005i0000005JKILAA4",
  "IsDeleted" : false,
  "Name" : "136",
  "CreatedDate" : "2019-07-10T14:39:34.000+0000",
  "CreatedById" : "005i0000005JKILAA4",
  "LastModifiedDate" : "2021-04-21T17:20:47.000+0000",
  "LastModifiedById" : "005i0000005JKILAA4",
  "SystemModstamp" : "2021-04-21T17:20:47.000+0000",
  "SBQQ__LookupField__c" : "CPQ_Not_For_All_Lines__c",
  "SBQQ__MatchType__c" : "Field Value",
  "SBQQ__Operator__c" : "equals",
  "SBQQ__ParentRuleIsActive__c" : false,
  "SBQQ__PriceRule2__c" : "a4R5A0000009qcyUAA",
  "SBQQ__RuleLookupObject__c" : "CPQ_Promotions__c",
  "SBQQ__RuleTargetsCalculator__c" : true,
  "SBQQ__TestedField__c" : "CPQ_Is_Blank__c",
  "SBQQ__TestedObject__c" : "Quote Line",
  "External_ID__c" : "4a81e2a70b448621b03b7c5fee419a34",
  "Active__c" : false
}