{
  "attributes" : {
    "type" : "SBQQ__ConfigurationAttribute__c",
    "url" : "/services/data/v55.0/sobjects/SBQQ__ConfigurationAttribute__c/a3x5A000000CF25QAG"
  },
  "Id" : "a3x5A000000CF25QAG",
  "OwnerId" : "005i0000005JKILAA4",
  "IsDeleted" : false,
  "Name" : "Number of Clicks",
  "CreatedDate" : "2019-07-10T12:59:42.000+0000",
  "CreatedById" : "005i0000005JKILAA4",
  "LastModifiedDate" : "2022-07-12T12:19:00.000+0000",
  "LastModifiedById" : "005i0000005JKILAA4",
  "SystemModstamp" : "2022-07-12T12:19:00.000+0000",
  "LastViewedDate" : "2022-08-15T18:12:44.000+0000",
  "LastReferencedDate" : "2022-08-15T18:12:44.000+0000",
  "SBQQ__AppliedImmediately__c" : false,
  "SBQQ__ApplyToProductOptions__c" : false,
  "SBQQ__AutoSelect__c" : false,
  "SBQQ__ColumnOrder__c" : "1",
  "SBQQ__DisplayOrder__c" : 1.0,
  "SBQQ__Global__c" : false,
  "SBQQ__Hidden__c" : false,
  "SBQQ__Position__c" : "Top",
  "SBQQ__Product__c" : "01t5A000008g9HsQAI",
  "SBQQ__Required__c" : true,
  "SBQQ__TargetField__c" : "CPQ_Number_of_Clicks__c",
  "External_ID__c" : "31b255e07b917ae63ab924436b2743be"
}