{
  "attributes" : {
    "type" : "Product2",
    "url" : "/services/data/v55.0/sobjects/Product2/01t55000009euLkAAI"
  },
  "Id" : "01t55000009euLkAAI",
  "Name" : "Social Ad Rebuild",
  "ProductCode" : "SOC-REBUILD-01",
  "IsActive" : true,
  "CreatedDate" : "2022-07-05T15:42:56.000+0000",
  "CreatedById" : "00531000007ZME4AAO",
  "LastModifiedDate" : "2022-08-01T14:35:53.000+0000",
  "LastModifiedById" : "00531000007ZME4AAO",
  "SystemModstamp" : "2022-08-01T14:35:53.000+0000",
  "Family" : "Digital-Social",
  "RecordTypeId" : "012i0000000tI4XAAU",
  "IsDeleted" : false,
  "IsArchived" : false,
  "LastViewedDate" : "2022-08-09T20:44:38.000+0000",
  "LastReferencedDate" : "2022-08-09T20:44:38.000+0000",
  "External_ID__c" : "cef203d98639d862c7fa26bacbe786fa",
  "SBQQ__AssetAmendmentBehavior__c" : "Allow Refund",
  "SBQQ__AssetConversion__c" : "One per quote line",
  "Anaplan_Level_2__c" : "Digital Performance",
  "Anaplan_Level_3__c" : "Social Family",
  "Anaplan_Level_4__c" : "Social Family - Other",
  "CPQ_Reinstate_Override__c" : false,
  "SBQQ__BlockPricingField__c" : "Quantity",
  "SBQQ__Component__c" : true,
  "SBQQ__CostEditable__c" : false,
  "SBQQ__CustomConfigurationRequired__c" : false,
  "SBQQ__DefaultQuantity__c" : 1.00000,
  "SBQQ__DescriptionLocked__c" : true,
  "SBQQ__ExcludeFromMaintenance__c" : false,
  "SBQQ__ExcludeFromOpportunity__c" : false,
  "SBQQ__ExternallyConfigurable__c" : false,
  "SBQQ__HasConfigurationAttributes__c" : false,
  "SBQQ__Hidden__c" : false,
  "SBQQ__HidePriceInSearchResults__c" : false,
  "SBQQ__IncludeInMaintenance__c" : false,
  "SBQQ__NewQuoteGroup__c" : false,
  "SBQQ__NonDiscountable__c" : false,
  "SBQQ__NonPartnerDiscountable__c" : false,
  "SBQQ__OptionSelectionMethod__c" : "Click",
  "SBQQ__Optional__c" : false,
  "SBQQ__PriceEditable__c" : false,
  "SBQQ__PricingMethodEditable__c" : false,
  "SBQQ__PricingMethod__c" : "List",
  "SBQQ__QuantityEditable__c" : true,
  "SBQQ__ReconfigurationDisabled__c" : false,
  "SBQQ__SortOrder__c" : 62,
  "SBQQ__SubscriptionBase__c" : "List",
  "SBQQ__SubscriptionPricing__c" : "Fixed Price",
  "SBQQ__SubscriptionTerm__c" : 1,
  "SBQQ__SubscriptionType__c" : "Renewable",
  "SBQQ__Taxable__c" : false,
  "CPQ_Bill__c" : false,
  "CPQ_Consultation_Type__c" : "POS;On Demand",
  "CPQ_Fulfill__c" : true,
  "CPQ_Product_Family_Search__c" : "Social",
  "CPQ_SAP_Description__c" : "Social Ad Rebuild",
  "CPQ_Cancel_Variable_Spend_Product__c" : false,
  "Item_Type__c" : "Adjustment/Discount",
  "Maintenance_Product__c" : false,
  "CPQ_Discount_cannot_be_Removed__c" : false,
  "Product_Category__c" : "Digital Marketing",
  "Product_Class__c" : "Adjustment/Discount",
  "CPQ_Listing_Category__c" : "No Listing;lawyer;Insurance;Dentist;Mortgage;Chiropractor;Attorney;Non Restricted;Local Ranking Restrictions",
  "Product_Sub_Category__c" : "Social Media",
  "CPQ_Profile_Filter__c" : "Hibu USA Tele-Sales Rep;System Administrator",
  "Product_Type__c" : "Digital",
  "CPQ_Term__c" : "0",
  "One_Time_Fee_Product__c" : false,
  "Product_Family__c" : "Social",
  "Sample_Extension2__c" : "TEST",
  "Sample_Extension3__c" : false,
  "CPQ_CurrentUserProfile_in_Profile_Filter__c" : true,
  "Is_Domain__c" : false,
  "Feature_Codes__c" : "INSTDATE",
  "SAP_Profit_Center__c" : 1050021,
  "Account_Assignment__c" : "ZG SAMI Def Setup Fees 240050 G/L",
  "Item_Category_Group__c" : "ZONO Serv Online w/o BP",
  "State_Tax__c" : "7 On Line Display",
  "County_Tax__c" : "7 On Line Display",
  "City_Tax__c" : "7 On Line Display",
  "Other_Tax__c" : "7 On Line Display",
  "CPQ_Include_in_Functionality__c" : "CalcMnthlyInvstmntOfOptins;AllowProdToBeCancelled",
  "IsBudgeted__c" : false,
  "Dashboard_SKU__c" : false,
  "Set_End_Date_From_Term__c" : false,
  "Hide_in_email__c" : false,
  "ProductCodeWithSemi__c" : "SOC-REBUILD-01;",
  "DoNotProrate__c" : false,
  "RCF_Valid__c" : false,
  "Inherit_Dates_From_Parent__c" : true,
  "Show_in_View__c" : false,
  "Reportable__c" : true,
  "POS_Fee__c" : false,
  "TreatAsBudgeted__c" : false,
  "Website_Related__c" : true,
  "ProrationProduct__c" : false,
  "Rebuild__c" : true,
  "Consultation_Required__c" : true
}