{
  "attributes" : {
    "type" : "SBQQ__PriceCondition__c",
    "url" : "/services/data/v55.0/sobjects/SBQQ__PriceCondition__c/a4Qf0000000OtgAEAS"
  },
  "Id" : "a4Qf0000000OtgAEAS",
  "IsDeleted" : false,
  "Name" : "1075",
  "CreatedDate" : "2020-07-08T12:57:58.000+0000",
  "CreatedById" : "005i0000005JKILAA4",
  "LastModifiedDate" : "2022-08-09T14:52:09.000+0000",
  "LastModifiedById" : "005i0000004afvgAAA",
  "SystemModstamp" : "2022-08-09T14:52:09.000+0000",
  "SBQQ__Rule__c" : "a4Rf0000000YNOoEAO",
  "SBQQ__FilterType__c" : "Value",
  "SBQQ__Index__c" : 11.0,
  "SBQQ__Object__c" : "Quote Line",
  "SBQQ__Operator__c" : "equals",
  "SBQQ__ParentRuleIsActive__c" : true,
  "SBQQ__RuleTargetsCalculator__c" : true,
  "SBQQ__TestedVariable__c" : "a4u5A000000TdCWQA0",
  "SBQQ__Value__c" : "1",
  "External_ID__c" : "d33a9795f83e0d6f426f85acc19a683a"
}