{
  "attributes" : {
    "type" : "SBQQ__ProductRule__c",
    "url" : "/services/data/v55.0/sobjects/SBQQ__ProductRule__c/a4c5A000000bGBEQA2"
  },
  "Id" : "a4c5A000000bGBEQA2",
  "OwnerId" : "005i0000005JKILAA4",
  "IsDeleted" : false,
  "Name" : "Upgrade Validation of Website Basic",
  "CreatedDate" : "2019-07-10T13:49:45.000+0000",
  "CreatedById" : "005i0000005JKILAA4",
  "LastModifiedDate" : "2022-05-18T12:41:18.000+0000",
  "LastModifiedById" : "005i0000005JKILAA4",
  "SystemModstamp" : "2022-05-18T12:41:18.000+0000",
  "SBQQ__Active__c" : true,
  "SBQQ__ConditionsMet__c" : "All",
  "SBQQ__ErrorMessage__c" : "If you are completing an Upsell you need to cancel the Website Basic and all associated child lines.",
  "SBQQ__EvaluationEvent__c" : "Always",
  "SBQQ__Scope__c" : "Quote",
  "SBQQ__Type__c" : "Validation",
  "External_ID__c" : "1c9f45fe62e1ae7743c199a6b8e3e975"
}