{
  "attributes" : {
    "type" : "SBQQ__ProductRule__c",
    "url" : "/services/data/v55.0/sobjects/SBQQ__ProductRule__c/a4c5A000000bGs4QAE"
  },
  "Id" : "a4c5A000000bGs4QAE",
  "OwnerId" : "005i0000005JKILAA4",
  "IsDeleted" : false,
  "Name" : "Cannot Downgrade Solution to Spread Bill Website",
  "CreatedDate" : "2019-08-12T20:41:16.000+0000",
  "CreatedById" : "005i0000005JKILAA4",
  "LastModifiedDate" : "2022-08-09T14:52:12.000+0000",
  "LastModifiedById" : "005i0000004afvgAAA",
  "SystemModstamp" : "2022-08-09T14:52:12.000+0000",
  "SBQQ__Active__c" : true,
  "SBQQ__AdvancedCondition__c" : "(1 AND 2 AND 3) OR (1 AND 4 AND 5)",
  "SBQQ__ConditionsMet__c" : "Custom",
  "SBQQ__ErrorMessage__c" : "You cannot downgrade a Solution Product to a Smart Site Spread Bill Website. You need to downgrade to the Smart Site Pro Website in order to waive the Design Fee.",
  "SBQQ__EvaluationEvent__c" : "Save",
  "SBQQ__EvaluationOrder__c" : 250.0,
  "SBQQ__Scope__c" : "Quote",
  "SBQQ__Type__c" : "Validation",
  "External_ID__c" : "b66ec14298a64ac7e2046edfb19d0953"
}